surfmesh/__init__.py
surfmesh/common.py
surfmesh/cuboid.py
surfmesh/cylinder.py
surfmesh/disk.py
surfmesh/edge.py
surfmesh/revolve.py
surfmesh/sphere.py
surfmesh-0.2.12.dist-info/METADATA
surfmesh-0.2.12.dist-info/WHEEL
surfmesh-0.2.12.dist-info/entry_points.txt
surfmesh-0.2.12.dist-info/licenses/LICENSE.txt
surfmesh-0.2.12.dist-info/RECORD
