Metadata-Version: 2.4
Name: surfmesh
Version: 0.2.12
Summary: A Python library to create simple 3D Surface Meshs using Quadrilateral dominant faces.
Project-URL: Homepage, https://github.com/ckesanapalli/surfmesh
Project-URL: GitHub, https://github.com/ckesanapalli/surfmesh
Project-URL: Documentation, https://github.com/ckesanapalli/surfmesh/blob/master/README.md
Project-URL: Bug, https://github.com/ckesanapalli/surfmesh/issues
Author-email: Chaitanya Kesanapalli <7126460+ckesanapalli@users.noreply.github.com>
License-File: LICENSE.txt
Classifier: Development Status :: 4 - Beta
Classifier: Intended Audience :: Science/Research
Classifier: License :: OSI Approved :: MIT License
Classifier: Programming Language :: Python :: 3.10
Classifier: Programming Language :: Python :: 3.11
Classifier: Programming Language :: Python :: 3.12
Classifier: Programming Language :: Python :: 3.13
Classifier: Topic :: Scientific/Engineering
Classifier: Topic :: Software Development :: Libraries :: Python Modules
Requires-Python: >=3.10
Requires-Dist: numpy>=1.24
Provides-Extra: dev
Requires-Dist: pytest-cov>=6.1.1; extra == 'dev'
Requires-Dist: pytest>=8.3.5; extra == 'dev'
Requires-Dist: ruff>=0.1.6; extra == 'dev'
Provides-Extra: examples
Requires-Dist: ipykernel>=6.29.5; extra == 'examples'
Requires-Dist: jupyterlab>=4.4.0; extra == 'examples'
Requires-Dist: matplotlib>=3.10.1; extra == 'examples'
